setup.cfg
setup.py
amp/__init__.py
amp/main.py
amp/player.py
amp/process.py
amp_player.egg-info/PKG-INFO
amp_player.egg-info/SOURCES.txt
amp_player.egg-info/dependency_links.txt
amp_player.egg-info/entry_points.txt
amp_player.egg-info/requires.txt
amp_player.egg-info/top_level.txt