Metadata-Version: 1.1
Name: amp-player
Version: 0.1.7
Summary: Asynchronous command-line YouTube interface
Home-page: https://github.com/nivekuil/amp
Author: Kevin Liu
Author-email: mail@nivekuil.com
License: GPL3
Download-URL: https://github.com/nivekuil/amp/tarball/master
Keywords: music,audio,video,stream,youtube
Platform: UNKNOWN
Classifier: Programming Language :: Python
